dnms_task-0.1.7.dist-info/METADATA
dnms_task-0.1.7.dist-info/WHEEL
dnms_task-0.1.7.dist-info/entry_points.txt
dnms_task/Gabor2D.bonsai
dnms_task/Gabor2D.bonsai.layout
dnms_task/Osc.config
dnms_task/__init__.py
dnms_task/task.py
dnms_task/task_parameters.yaml
dnms_task-0.1.7.dist-info/RECORD
