Metadata-Version: 2.1
Name: dnms-task
Version: 0.1.7
Summary: Delayed Non-Match-To-Sample task for IBLRIG
Keywords: IBL,neuro-science
Author-Email: "Tatiana Dupak (University of Bordeaux)" <tatiana.dupak@u-bordeaux.fr>
License: MIT
Requires-Python: >=3.10
